{
  "color": {
    "border": {
      "primary": {
        "onLight": {
          "value": "{color.base.black-opacity-15.value}",
          "public": true,
          "usage": "Primary border color on light backgrounds",
          "wcag": "n/a"
        },
        "onDark": {
          "value": "{color.base.white-opacity-40.value}",
          "public": true,
          "usage": "Primary border color on dark background",
          "wcag": "n/a"
        }
      },
      "active": {
        "onLight": {
          "value": "{color.base.ui.value}",
          "public": true,
          "usage": "Active border color on light backgrounds",
          "wcag": "n/a"
        },
        "onDark": {
          "value": "{color.brand.breeze.300.value}",
          "public": true,
          "usage": "Active border color on dark backgrounds",
          "wcag": "n/a"
        }
      },
      "error": {
        "onLight": {
          "value": "{color.base.crimson.500.value}",
          "public": true,
          "usage": "Error states border color on light backgrounds",
          "wcag": "n/a"
        },
        "onDark": {
          "value": "{color.base.crimson.100.value}",
          "public": true,
          "usage": "Error states border color on dark background",
          "wcag": "n/a"
        }
      },
      "disabled": {
        "onLight": {
          "value": "{color.base.disabled.value}",
          "public": true,
          "usage": "Disabled border color on light backgrounds",
          "wcag": "n/a"
        },
        "onDark": {
          "value": "{color.base.disabled.value}",
          "public": true,
          "usage": "Disabled border color on dark background",
          "wcag": "n/a"
        }
      }
    }
  }
}
