{
  "color": {
    "classic": {
      "gray": {
        "100": {
          "value": "f7f7f7",
          "comment": "",
          "public": true,
          "neutral": true,
          "usage": "",
          "wcag": "n/a",
          "deprecated": false
        },
        "200": {
          "value": "dddddd",
          "comment": "",
          "public": true,
          "neutral": true,
          "usage": "",
          "wcag": "n/a",
          "deprecated": false
        },
        "300": {
          "value": "c5c5c5",
          "comment": "",
          "public": true,
          "neutral": true,
          "usage": "",
          "wcag": "n/a",
          "deprecated": false
        },
        "400": {
          "value": "adadad",
          "comment": "",
          "public": true,
          "neutral": true,
          "usage": "",
          "wcag": "n/a",
          "deprecated": false
        },
        "500": {
          "value": "959595",
          "comment": "",
          "public": true,
          "neutral": true,
          "usage": "",
          "wcag": "n/a",
          "deprecated": false
        },
        "600": {
          "value": "7e7e7e",
          "comment": "",
          "public": true,
          "neutral": true,
          "usage": "",
          "wcag": "n/a",
          "deprecated": false
        },
        "700": {
          "value": "676767",
          "comment": "",
          "public": true,
          "neutral": true,
          "usage": "",
          "wcag": "n/a",
          "deprecated": false
        },
        "800": {
          "value": "525252",
          "comment": "",
          "public": true,
          "neutral": true,
          "usage": "",
          "wcag": "n/a",
          "deprecated": false
        },
        "900": {
          "value": "3d3d3d",
          "comment": "",
          "public": true,
          "neutral": true,
          "usage": "",
          "wcag": "n/a",
          "deprecated": false
        },
        "1000": {
          "value": "2a2a2a",
          "comment": "",
          "public": true,
          "neutral": true,
          "usage": "",
          "wcag": "n/a",
          "deprecated": false
        }
      },
      "neutral": {
        "100": {
          "value": "f7f8fa",
          "comment": "",
          "public": true,
          "neutral": true,
          "usage": "",
          "wcag": "n/a",
          "deprecated": false
        },
        "200": {
          "value": "e4e8ec",
          "comment": "",
          "public": true,
          "neutral": true,
          "usage": "",
          "wcag": "n/a",
          "deprecated": false
        },
        "300": {
          "value": "ccd2db",
          "comment": "",
          "public": true,
          "neutral": true,
          "usage": "",
          "wcag": "n/a",
          "deprecated": false
        },
        "400": {
          "value": "afb9c6",
          "comment": "",
          "public": true,
          "neutral": true,
          "usage": "",
          "wcag": "n/a",
          "deprecated": false
        },
        "500": {
          "value": "939fad",
          "comment": "",
          "public": true,
          "neutral": true,
          "usage": "",
          "wcag": "n/a",
          "deprecated": false
        },
        "600": {
          "value": "7e8894",
          "comment": "",
          "public": true,
          "neutral": true,
          "usage": "",
          "wcag": "n/a",
          "deprecated": false
        },
        "700": {
          "value": "6a717c",
          "comment": "",
          "public": true,
          "neutral": true,
          "usage": "",
          "wcag": "n/a",
          "deprecated": false
        },
        "800": {
          "value": "585e67",
          "comment": "",
          "public": true,
          "neutral": true,
          "usage": "",
          "wcag": "n/a",
          "deprecated": false
        },
        "900": {
          "value": "484d55",
          "comment": "",
          "public": true,
          "neutral": true,
          "usage": "",
          "wcag": "n/a",
          "deprecated": false
        },
        "1000": {
          "value": "393d43",
          "comment": "",
          "public": true,
          "neutral": true,
          "usage": "",
          "wcag": "n/a",
          "deprecated": false
        }
      },
      "cyan": {
        "100": {
          "value": "ebfafd",
          "comment": "",
          "public": true,
          "neutral": true,
          "usage": "",
          "wcag": "n/a",
          "deprecated": false
        },
        "200": {
          "value": "a8e9f7",
          "comment": "",
          "public": true,
          "neutral": true,
          "usage": "",
          "wcag": "n/a",
          "deprecated": false
        },
        "300": {
          "value": "6ad5ef",
          "comment": "",
          "public": true,
          "neutral": true,
          "usage": "",
          "wcag": "n/a",
          "deprecated": false
        },
        "400": {
          "value": "56bbde",
          "comment": "",
          "public": true,
          "neutral": true,
          "usage": "",
          "wcag": "n/a",
          "deprecated": false
        },
        "500": {
          "value": "4aa2c7",
          "comment": "",
          "public": true,
          "neutral": true,
          "usage": "",
          "wcag": "n/a",
          "deprecated": false
        },
        "600": {
          "value": "3e89aa",
          "comment": "",
          "public": true,
          "neutral": true,
          "usage": "",
          "wcag": "n/a",
          "deprecated": false
        },
        "700": {
          "value": "32718e",
          "comment": "",
          "public": true,
          "neutral": true,
          "usage": "",
          "wcag": "n/a",
          "deprecated": false
        },
        "800": {
          "value": "275b72",
          "comment": "",
          "public": true,
          "neutral": true,
          "usage": "",
          "wcag": "n/a",
          "deprecated": false
        },
        "900": {
          "value": "1d4658",
          "comment": "",
          "public": true,
          "neutral": true,
          "usage": "",
          "wcag": "n/a",
          "deprecated": false
        },
        "1000": {
          "value": "12303d",
          "comment": "",
          "public": true,
          "neutral": true,
          "usage": "",
          "wcag": "n/a",
          "deprecated": false
        }
      },
      "blue": {
        "100": {
          "value": "ffffff",
          "comment": "",
          "public": true,
          "neutral": true,
          "usage": "",
          "wcag": "n/a",
          "deprecated": false
        },
        "200": {
          "value": "ffffff",
          "comment": "",
          "public": true,
          "neutral": true,
          "usage": "",
          "wcag": "n/a",
          "deprecated": false
        },
        "300": {
          "value": "ffffff",
          "comment": "",
          "public": true,
          "neutral": true,
          "usage": "",
          "wcag": "n/a",
          "deprecated": false
        },
        "400": {
          "value": "ffffff",
          "comment": "",
          "public": true,
          "neutral": true,
          "usage": "",
          "wcag": "n/a",
          "deprecated": false
        },
        "500": {
          "value": "ffffff",
          "comment": "",
          "public": true,
          "neutral": true,
          "usage": "",
          "wcag": "n/a",
          "deprecated": false
        },
        "600": {
          "value": "ffffff",
          "comment": "",
          "public": true,
          "neutral": true,
          "usage": "",
          "wcag": "n/a",
          "deprecated": false
        },
        "700": {
          "value": "ffffff",
          "comment": "",
          "public": true,
          "neutral": true,
          "usage": "",
          "wcag": "n/a",
          "deprecated": false
        },
        "800": {
          "value": "ffffff",
          "comment": "",
          "public": true,
          "neutral": true,
          "usage": "",
          "wcag": "n/a",
          "deprecated": false
        },
        "900": {
          "value": "ffffff",
          "comment": "",
          "public": true,
          "neutral": true,
          "usage": "",
          "wcag": "n/a",
          "deprecated": false
        },
        "1000": {
          "value": "ffffff",
          "comment": "",
          "public": true,
          "neutral": true,
          "usage": "",
          "wcag": "n/a",
          "deprecated": false
        }
      },
      "navy": {
        "100": {
          "value": "ffffff",
          "comment": "",
          "public": true,
          "neutral": true,
          "usage": "",
          "wcag": "n/a",
          "deprecated": false
        },
        "200": {
          "value": "ffffff",
          "comment": "",
          "public": true,
          "neutral": true,
          "usage": "",
          "wcag": "n/a",
          "deprecated": false
        },
        "300": {
          "value": "ffffff",
          "comment": "",
          "public": true,
          "neutral": true,
          "usage": "",
          "wcag": "n/a",
          "deprecated": false
        },
        "400": {
          "value": "ffffff",
          "comment": "",
          "public": true,
          "neutral": true,
          "usage": "",
          "wcag": "n/a",
          "deprecated": false
        },
        "500": {
          "value": "ffffff",
          "comment": "",
          "public": true,
          "neutral": true,
          "usage": "",
          "wcag": "n/a",
          "deprecated": false
        },
        "600": {
          "value": "ffffff",
          "comment": "",
          "public": true,
          "neutral": true,
          "usage": "",
          "wcag": "n/a",
          "deprecated": false
        },
        "700": {
          "value": "ffffff",
          "comment": "",
          "public": true,
          "neutral": true,
          "usage": "",
          "wcag": "n/a",
          "deprecated": false
        },
        "800": {
          "value": "ffffff",
          "comment": "",
          "public": true,
          "neutral": true,
          "usage": "",
          "wcag": "n/a",
          "deprecated": false
        },
        "900": {
          "value": "ffffff",
          "comment": "",
          "public": true,
          "neutral": true,
          "usage": "",
          "wcag": "n/a",
          "deprecated": false
        },
        "1000": {
          "value": "ffffff",
          "comment": "",
          "public": true,
          "neutral": true,
          "usage": "",
          "wcag": "n/a",
          "deprecated": false
        }
      },
      "turquoise": {
        "100": {
          "value": "ffffff",
          "comment": "",
          "public": true,
          "neutral": true,
          "usage": "",
          "wcag": "n/a",
          "deprecated": false
        },
        "200": {
          "value": "ffffff",
          "comment": "",
          "public": true,
          "neutral": true,
          "usage": "",
          "wcag": "n/a",
          "deprecated": false
        },
        "300": {
          "value": "ffffff",
          "comment": "",
          "public": true,
          "neutral": true,
          "usage": "",
          "wcag": "n/a",
          "deprecated": false
        },
        "400": {
          "value": "ffffff",
          "comment": "",
          "public": true,
          "neutral": true,
          "usage": "",
          "wcag": "n/a",
          "deprecated": false
        },
        "500": {
          "value": "ffffff",
          "comment": "",
          "public": true,
          "neutral": true,
          "usage": "",
          "wcag": "n/a",
          "deprecated": false
        },
        "600": {
          "value": "ffffff",
          "comment": "",
          "public": true,
          "neutral": true,
          "usage": "",
          "wcag": "n/a",
          "deprecated": false
        },
        "700": {
          "value": "ffffff",
          "comment": "",
          "public": true,
          "neutral": true,
          "usage": "",
          "wcag": "n/a",
          "deprecated": false
        },
        "800": {
          "value": "ffffff",
          "comment": "",
          "public": true,
          "neutral": true,
          "usage": "",
          "wcag": "n/a",
          "deprecated": false
        },
        "900": {
          "value": "ffffff",
          "comment": "",
          "public": true,
          "neutral": true,
          "usage": "",
          "wcag": "n/a",
          "deprecated": false
        },
        "1000": {
          "value": "ffffff",
          "comment": "",
          "public": true,
          "neutral": true,
          "usage": "",
          "wcag": "n/a",
          "deprecated": false
        }
      },
      "green": {
        "100": {
          "value": "ffffff",
          "comment": "",
          "public": true,
          "neutral": true,
          "usage": "",
          "wcag": "n/a",
          "deprecated": false
        },
        "200": {
          "value": "ffffff",
          "comment": "",
          "public": true,
          "neutral": true,
          "usage": "",
          "wcag": "n/a",
          "deprecated": false
        },
        "300": {
          "value": "ffffff",
          "comment": "",
          "public": true,
          "neutral": true,
          "usage": "",
          "wcag": "n/a",
          "deprecated": false
        },
        "400": {
          "value": "ffffff",
          "comment": "",
          "public": true,
          "neutral": true,
          "usage": "",
          "wcag": "n/a",
          "deprecated": false
        },
        "500": {
          "value": "ffffff",
          "comment": "",
          "public": true,
          "neutral": true,
          "usage": "",
          "wcag": "n/a",
          "deprecated": false
        },
        "600": {
          "value": "ffffff",
          "comment": "",
          "public": true,
          "neutral": true,
          "usage": "",
          "wcag": "n/a",
          "deprecated": false
        },
        "700": {
          "value": "ffffff",
          "comment": "",
          "public": true,
          "neutral": true,
          "usage": "",
          "wcag": "n/a",
          "deprecated": false
        },
        "800": {
          "value": "ffffff",
          "comment": "",
          "public": true,
          "neutral": true,
          "usage": "",
          "wcag": "n/a",
          "deprecated": false
        },
        "900": {
          "value": "ffffff",
          "comment": "",
          "public": true,
          "neutral": true,
          "usage": "",
          "wcag": "n/a",
          "deprecated": false
        },
        "1000": {
          "value": "ffffff",
          "comment": "",
          "public": true,
          "neutral": true,
          "usage": "",
          "wcag": "n/a",
          "deprecated": false
        }
      },
      "lime": {
        "100": {
          "value": "ffffff",
          "comment": "",
          "public": true,
          "neutral": true,
          "usage": "",
          "wcag": "n/a",
          "deprecated": false
        },
        "200": {
          "value": "ffffff",
          "comment": "",
          "public": true,
          "neutral": true,
          "usage": "",
          "wcag": "n/a",
          "deprecated": false
        },
        "300": {
          "value": "ffffff",
          "comment": "",
          "public": true,
          "neutral": true,
          "usage": "",
          "wcag": "n/a",
          "deprecated": false
        },
        "400": {
          "value": "ffffff",
          "comment": "",
          "public": true,
          "neutral": true,
          "usage": "",
          "wcag": "n/a",
          "deprecated": false
        },
        "500": {
          "value": "ffffff",
          "comment": "",
          "public": true,
          "neutral": true,
          "usage": "",
          "wcag": "n/a",
          "deprecated": false
        },
        "600": {
          "value": "ffffff",
          "comment": "",
          "public": true,
          "neutral": true,
          "usage": "",
          "wcag": "n/a",
          "deprecated": false
        },
        "700": {
          "value": "ffffff",
          "comment": "",
          "public": true,
          "neutral": true,
          "usage": "",
          "wcag": "n/a",
          "deprecated": false
        },
        "800": {
          "value": "ffffff",
          "comment": "",
          "public": true,
          "neutral": true,
          "usage": "",
          "wcag": "n/a",
          "deprecated": false
        },
        "900": {
          "value": "ffffff",
          "comment": "",
          "public": true,
          "neutral": true,
          "usage": "",
          "wcag": "n/a",
          "deprecated": false
        },
        "1000": {
          "value": "ffffff",
          "comment": "",
          "public": true,
          "neutral": true,
          "usage": "",
          "wcag": "n/a",
          "deprecated": false
        }
      },
      "yellow": {
        "100": {
          "value": "ffffff",
          "comment": "",
          "public": true,
          "neutral": true,
          "usage": "",
          "wcag": "n/a",
          "deprecated": false
        },
        "200": {
          "value": "ffffff",
          "comment": "",
          "public": true,
          "neutral": true,
          "usage": "",
          "wcag": "n/a",
          "deprecated": false
        },
        "300": {
          "value": "ffffff",
          "comment": "",
          "public": true,
          "neutral": true,
          "usage": "",
          "wcag": "n/a",
          "deprecated": false
        },
        "400": {
          "value": "ffffff",
          "comment": "",
          "public": true,
          "neutral": true,
          "usage": "",
          "wcag": "n/a",
          "deprecated": false
        },
        "500": {
          "value": "ffffff",
          "comment": "",
          "public": true,
          "neutral": true,
          "usage": "",
          "wcag": "n/a",
          "deprecated": false
        },
        "600": {
          "value": "ffffff",
          "comment": "",
          "public": true,
          "neutral": true,
          "usage": "",
          "wcag": "n/a",
          "deprecated": false
        },
        "700": {
          "value": "ffffff",
          "comment": "",
          "public": true,
          "neutral": true,
          "usage": "",
          "wcag": "n/a",
          "deprecated": false
        },
        "800": {
          "value": "ffffff",
          "comment": "",
          "public": true,
          "neutral": true,
          "usage": "",
          "wcag": "n/a",
          "deprecated": false
        },
        "900": {
          "value": "ffffff",
          "comment": "",
          "public": true,
          "neutral": true,
          "usage": "",
          "wcag": "n/a",
          "deprecated": false
        },
        "1000": {
          "value": "ffffff",
          "comment": "",
          "public": true,
          "neutral": true,
          "usage": "",
          "wcag": "n/a",
          "deprecated": false
        }
      },
      "red": {
        "100": {
          "value": "ffffff",
          "comment": "",
          "public": true,
          "neutral": true,
          "usage": "",
          "wcag": "n/a",
          "deprecated": false
        },
        "200": {
          "value": "ffffff",
          "comment": "",
          "public": true,
          "neutral": true,
          "usage": "",
          "wcag": "n/a",
          "deprecated": false
        },
        "300": {
          "value": "ffffff",
          "comment": "",
          "public": true,
          "neutral": true,
          "usage": "",
          "wcag": "n/a",
          "deprecated": false
        },
        "400": {
          "value": "ffffff",
          "comment": "",
          "public": true,
          "neutral": true,
          "usage": "",
          "wcag": "n/a",
          "deprecated": false
        },
        "500": {
          "value": "ffffff",
          "comment": "",
          "public": true,
          "neutral": true,
          "usage": "",
          "wcag": "n/a",
          "deprecated": false
        },
        "600": {
          "value": "ffffff",
          "comment": "",
          "public": true,
          "neutral": true,
          "usage": "",
          "wcag": "n/a",
          "deprecated": false
        },
        "700": {
          "value": "ffffff",
          "comment": "",
          "public": true,
          "neutral": true,
          "usage": "",
          "wcag": "n/a",
          "deprecated": false
        },
        "800": {
          "value": "ffffff",
          "comment": "",
          "public": true,
          "neutral": true,
          "usage": "",
          "wcag": "n/a",
          "deprecated": false
        },
        "900": {
          "value": "ffffff",
          "comment": "",
          "public": true,
          "neutral": true,
          "usage": "",
          "wcag": "n/a",
          "deprecated": false
        },
        "1000": {
          "value": "ffffff",
          "comment": "",
          "public": true,
          "neutral": true,
          "usage": "",
          "wcag": "n/a",
          "deprecated": false
        }
      },
      "pink": {
        "100": {
          "value": "ffffff",
          "comment": "",
          "public": true,
          "neutral": true,
          "usage": "",
          "wcag": "n/a",
          "deprecated": false
        },
        "200": {
          "value": "ffffff",
          "comment": "",
          "public": true,
          "neutral": true,
          "usage": "",
          "wcag": "n/a",
          "deprecated": false
        },
        "300": {
          "value": "ffffff",
          "comment": "",
          "public": true,
          "neutral": true,
          "usage": "",
          "wcag": "n/a",
          "deprecated": false
        },
        "400": {
          "value": "ffffff",
          "comment": "",
          "public": true,
          "neutral": true,
          "usage": "",
          "wcag": "n/a",
          "deprecated": false
        },
        "500": {
          "value": "ffffff",
          "comment": "",
          "public": true,
          "neutral": true,
          "usage": "",
          "wcag": "n/a",
          "deprecated": false
        },
        "600": {
          "value": "ffffff",
          "comment": "",
          "public": true,
          "neutral": true,
          "usage": "",
          "wcag": "n/a",
          "deprecated": false
        },
        "700": {
          "value": "ffffff",
          "comment": "",
          "public": true,
          "neutral": true,
          "usage": "",
          "wcag": "n/a",
          "deprecated": false
        },
        "800": {
          "value": "ffffff",
          "comment": "",
          "public": true,
          "neutral": true,
          "usage": "",
          "wcag": "n/a",
          "deprecated": false
        },
        "900": {
          "value": "ffffff",
          "comment": "",
          "public": true,
          "neutral": true,
          "usage": "",
          "wcag": "n/a",
          "deprecated": false
        },
        "1000": {
          "value": "ffffff",
          "comment": "",
          "public": true,
          "neutral": true,
          "usage": "",
          "wcag": "n/a",
          "deprecated": false
        }
      },
      "purple": {
        "100": {
          "value": "ffffff",
          "comment": "",
          "public": true,
          "neutral": true,
          "usage": "",
          "wcag": "n/a",
          "deprecated": false
        },
        "200": {
          "value": "ffffff",
          "comment": "",
          "public": true,
          "neutral": true,
          "usage": "",
          "wcag": "n/a",
          "deprecated": false
        },
        "300": {
          "value": "ffffff",
          "comment": "",
          "public": true,
          "neutral": true,
          "usage": "",
          "wcag": "n/a",
          "deprecated": false
        },
        "400": {
          "value": "ffffff",
          "comment": "",
          "public": true,
          "neutral": true,
          "usage": "",
          "wcag": "n/a",
          "deprecated": false
        },
        "500": {
          "value": "ffffff",
          "comment": "",
          "public": true,
          "neutral": true,
          "usage": "",
          "wcag": "n/a",
          "deprecated": false
        },
        "600": {
          "value": "ffffff",
          "comment": "",
          "public": true,
          "neutral": true,
          "usage": "",
          "wcag": "n/a",
          "deprecated": false
        },
        "700": {
          "value": "ffffff",
          "comment": "",
          "public": true,
          "neutral": true,
          "usage": "",
          "wcag": "n/a",
          "deprecated": false
        },
        "800": {
          "value": "ffffff",
          "comment": "",
          "public": true,
          "neutral": true,
          "usage": "",
          "wcag": "n/a",
          "deprecated": false
        },
        "900": {
          "value": "ffffff",
          "comment": "",
          "public": true,
          "neutral": true,
          "usage": "",
          "wcag": "n/a",
          "deprecated": false
        },
        "1000": {
          "value": "ffffff",
          "comment": "",
          "public": true,
          "neutral": true,
          "usage": "",
          "wcag": "n/a",
          "deprecated": false
        }
      }
    },
    "brand": {
      "midnight": {
        "100": {
          "value": "c1daf0",
          "comment": "{comments.color.brand.value.comment}",
          "public": true,
          "neutral": true,
          "usage": "Transactional colors to move guests through task-based interactions.",
          "wcag": "n/a",
          "deprecated": true
        },
        "200": {
          "value": "569ed7",
          "comment": "{comments.color.brand.value.comment}",
          "public": true,
          "neutral": true,
          "usage": "Transactional colors to move guests through task-based interactions.",
          "wcag": "n/a",
          "deprecated": true
        },
        "300": {
          "value": "156fad",
          "comment": "{comments.color.brand.value.comment}",
          "public": true,
          "neutral": true,
          "usage": "Transactional colors to move guests through task-based interactions.",
          "wcag": "n/a",
          "deprecated": true
        },
        "400": {
          "value": "01426a",
          "comment": "{comments.color.brand.value.comment}",
          "public": true,
          "neutral": true,
          "usage": "Transactional colors to move guests through task-based interactions.",
          "wcag": "n/a",
          "deprecated": true
        },
        "500": {
          "value": "00274a",
          "comment": "{comments.color.brand.value.comment}",
          "public": true,
          "neutral": true,
          "usage": "Transactional colors to move guests through task-based interactions.",
          "wcag": "n/a",
          "deprecated": true
        }
      },
      "atlas": {
        "100": {
          "value": "cde6ff",
          "comment": "{comments.color.brand.value.comment}",
          "public": true,
          "neutral": true,
          "usage": "Transactional colors to move guests through task-based interactions.",
          "wcag": "n/a",
          "deprecated": true
        },
        "200": {
          "value": "6bb7fb",
          "comment": "{comments.color.brand.value.comment}",
          "public": true,
          "neutral": true,
          "usage": "Transactional colors to move guests through task-based interactions.",
          "wcag": "n/a",
          "deprecated": true
        },
        "300": {
          "value": "2492eb",
          "comment": "{comments.color.brand.value.comment}",
          "public": true,
          "neutral": true,
          "usage": "Transactional colors to move guests through task-based interactions.",
          "wcag": "n/a",
          "deprecated": true
        },
        "400": {
          "value": "0074c8",
          "comment": "{comments.color.brand.value.comment}",
          "public": true,
          "neutral": true,
          "usage": "Transactional colors to move guests through task-based interactions.",
          "wcag": "n/a",
          "deprecated": true
        },
        "400-opacity-20": {
          "value": "0074c833",
          "comment": "color brand atlas 400 @ 20%",
          "opacity": true
        },
        "500": {
          "value": "054687",
          "comment": "{comments.color.brand.value.comment}",
          "public": true,
          "neutral": true,
          "usage": "Transactional colors to move guests through task-based interactions.",
          "wcag": "n/a",
          "deprecated": true
        }
      },
      "breeze": {
        "100": {
          "value": "c0f7ff",
          "comment": "{comments.color.brand.value.comment}",
          "public": true,
          "neutral": true,
          "usage": "Transactional colors to move guests through task-based interactions.",
          "wcag": "n/a",
          "deprecated": true
        },
        "200": {
          "value": "5de3f7",
          "comment": "{comments.color.brand.value.comment}",
          "public": true,
          "neutral": true,
          "usage": "Transactional colors to move guests through task-based interactions.",
          "wcag": "n/a",
          "deprecated": true
        },
        "300": {
          "value": "00cff0",
          "public": true,
          "comment": "{comments.color.brand.value.comment}",
          "neutral": true,
          "usage": "Transactional colors to move guests through task-based interactions.",
          "wcag": "n/a",
          "deprecated": true
        },
        "300-opacity-30": {
          "value": "00cff04d",
          "comment": "breeze 300 @ 30%",
          "neutral": true,
          "usage": "Transactional colors to move guests through task-based interactions.",
          "wcag": "n/a",
          "deprecated": true
        },
        "400": {
          "value": "099dc5",
          "public": true,
          "comment": "{comments.color.brand.value.comment}",
          "neutral": true,
          "usage": "Transactional colors to move guests through task-based interactions.",
          "wcag": "n/a",
          "deprecated": true
        },
        "500": {
          "value": "0b5575",
          "public": true,
          "comment": "{comments.color.brand.value.comment}",
          "neutral": true,
          "usage": "Transactional colors to move guests through task-based interactions.",
          "wcag": "n/a",
          "deprecated": true
        }
      },
      "tropical": {
        "100": {
          "value": "e2ffcd",
          "public": true,
          "comment": "{comments.color.brand.value.comment}",
          "neutral": true,
          "usage": "Transactional colors to move guests through task-based interactions.",
          "wcag": "n/a",
          "deprecated": true
        },
        "200": {
          "value": "d0fba6",
          "public": true,
          "comment": "{comments.color.brand.value.comment}",
          "neutral": true,
          "usage": "Transactional colors to move guests through task-based interactions.",
          "wcag": "n/a",
          "deprecated": true
        },
        "300": {
          "value": "c0e585",
          "public": true,
          "comment": "{comments.color.brand.value.comment}",
          "neutral": true,
          "usage": "Transactional colors to move guests through task-based interactions.",
          "wcag": "n/a",
          "deprecated": true
        },
        "400": {
          "value": "91be62",
          "public": true,
          "comment": "{comments.color.brand.value.comment}",
          "neutral": true,
          "usage": "Transactional colors to move guests through task-based interactions.",
          "wcag": "n/a",
          "deprecated": true
        },
        "500": {
          "value": "5e8741",
          "public": true,
          "comment": "{comments.color.brand.value.comment}",
          "neutral": true,
          "usage": "Transactional colors to move guests through task-based interactions.",
          "wcag": "n/a",
          "deprecated": true
        }
      },
      "alpine": {
        "100": {
          "value": "bcaae6",
          "public": true,
          "comment": "{comments.color.brand.value.comment}",
          "neutral": true,
          "usage": "Conversational colors add warmth and energy to our experience",
          "wcag": "n/a",
          "deprecated": true
        },
        "200": {
          "value": "9e73ea",
          "public": true,
          "comment": "{comments.color.brand.value.comment}",
          "neutral": true,
          "usage": "Conversational colors add warmth and energy to our experience",
          "wcag": "n/a",
          "deprecated": true
        },
        "300": {
          "value": "8439ef",
          "public": true,
          "comment": "{comments.color.brand.value.comment}",
          "neutral": true,
          "usage": "Conversational colors add warmth and energy to our experience",
          "wcag": "n/a",
          "deprecated": true
        },
        "400": {
          "value": "631db8",
          "public": true,
          "comment": "{comments.color.brand.value.comment}",
          "neutral": true,
          "usage": "Conversational colors add warmth and energy to our experience",
          "wcag": "n/a",
          "deprecated": true
        },
        "500": {
          "value": "39115c",
          "public": true,
          "comment": "{comments.color.brand.value.comment}",
          "neutral": true,
          "usage": "Conversational colors add warmth and energy to our experience",
          "wcag": "n/a",
          "deprecated": true
        }
      },
      "flamingo": {
        "100": {
          "value": "ffebee",
          "public": true,
          "comment": "{comments.color.brand.value.comment}",
          "neutral": true,
          "usage": "Conversational colors add warmth and energy to our experience",
          "wcag": "n/a",
          "deprecated": true
        },
        "200": {
          "value": "ffc0ca",
          "public": true,
          "comment": "{comments.color.brand.value.comment}",
          "neutral": true,
          "usage": "Conversational colors add warmth and energy to our experience",
          "wcag": "n/a",
          "deprecated": true
        },
        "300": {
          "value": "ff94a7",
          "public": true,
          "comment": "{comments.color.brand.value.comment}",
          "neutral": true,
          "usage": "Conversational colors add warmth and energy to our experience",
          "wcag": "n/a",
          "deprecated": true
        },
        "400": {
          "value": "F65b7b",
          "public": true,
          "comment": "{comments.color.brand.value.comment}",
          "neutral": true,
          "usage": "Conversational colors add warmth and energy to our experience",
          "wcag": "n/a",
          "deprecated": true
        },
        "500": {
          "value": "b82b47",
          "public": true,
          "comment": "{comments.color.brand.value.comment}",
          "neutral": true,
          "usage": "Conversational colors add warmth and energy to our experience",
          "wcag": "n/a",
          "deprecated": true
        }
      },
      "canyon": {
        "100": {
          "value": "ffcab6",
          "public": true,
          "comment": "{comments.color.brand.value.comment}",
          "neutral": true,
          "usage": "Conversational colors add warmth and energy to our experience",
          "wcag": "n/a",
          "deprecated": true
        },
        "200": {
          "value": "f99574",
          "public": true,
          "comment": "{comments.color.brand.value.comment}",
          "neutral": true,
          "usage": "Conversational colors add warmth and energy to our experience",
          "wcag": "n/a",
          "deprecated": true
        },
        "300": {
          "value": "f26135",
          "public": true,
          "comment": "{comments.color.brand.value.comment}",
          "neutral": true,
          "usage": "Conversational colors add warmth and energy to our experience",
          "wcag": "n/a",
          "deprecated": true
        },
        "400": {
          "value": "de3e09",
          "public": true,
          "comment": "{comments.color.brand.value.comment}",
          "neutral": true,
          "usage": "Conversational colors add warmth and energy to our experience",
          "wcag": "n/a",
          "deprecated": true
        },
        "500": {
          "value": "b83302",
          "public": true,
          "comment": "{comments.color.brand.value.comment}",
          "neutral": true,
          "usage": "Conversational colors add warmth and energy to our experience",
          "wcag": "n/a",
          "deprecated": true
        }
      },
      "goldcoast": {
        "100": {
          "value": "fff0cd",
          "public": true,
          "comment": "{comments.color.brand.value.comment}",
          "neutral": true,
          "usage": "Conversational colors add warmth and energy to our experience",
          "wcag": "n/a",
          "deprecated": true
        },
        "200": {
          "value": "ffdb67",
          "public": true,
          "comment": "{comments.color.brand.value.comment}",
          "neutral": true,
          "usage": "Conversational colors add warmth and energy to our experience",
          "wcag": "n/a",
          "deprecated": true
        },
        "300": {
          "value": "ffd200",
          "public": true,
          "comment": "{comments.color.brand.value.comment}",
          "neutral": true,
          "usage": "Conversational colors add warmth and energy to our experience",
          "wcag": "n/a",
          "deprecated": true
        },
        "400": {
          "value": "e5ad07",
          "public": true,
          "comment": "{comments.color.brand.value.comment}",
          "neutral": true,
          "usage": "Conversational colors add warmth and energy to our experience",
          "wcag": "n/a",
          "deprecated": true
        },
        "500": {
          "value": "b88624",
          "public": true,
          "comment": "{comments.color.brand.value.comment}",
          "neutral": true,
          "usage": "Conversational colors add warmth and energy to our experience",
          "wcag": "n/a",
          "deprecated": true
        }
      },
      "neutral": {
        "100": {
          "value": "f9fbfc",
          "public": true,
          "comment": "{comments.color.brand.value.comment}",
          "neutral": true,
          "usage": "TBD...",
          "wcag": "n/a",
          "deprecated": true
        },
        "200": {
          "value": "e2eaef",
          "public": true,
          "comment": "{comments.color.brand.value.comment}",
          "neutral": true,
          "usage": "TBD...",
          "wcag": "n/a",
          "deprecated": true
        },
        "300": {
          "value": "cbd8e2",
          "public": true,
          "comment": "{comments.color.brand.value.comment}",
          "neutral": true,
          "usage": "TBD...",
          "wcag": "n/a",
          "deprecated": true
        },
        "400": {
          "value": "9fabbb",
          "public": true,
          "comment": "{comments.color.brand.value.comment}",
          "neutral": true,
          "usage": "TBD...",
          "wcag": "n/a",
          "deprecated": true
        },
        "500": {
          "value": "626b79",
          "public": true,
          "comment": "{comments.color.brand.value.comment}",
          "neutral": true,
          "usage": "TBD...",
          "wcag": "n/a",
          "deprecated": true
        }
      },
      "goldgray": {
        "100": {
          "value": "C5C1BF",
          "public": true,
          "usage": "Tier branding color",
          "deprecated": true
        },
        "200": {
          "value": "726E6C",
          "public": true,
          "usage": "Tier branding color",
          "deprecated": true
        }
      },
      "gold": {
        "100": {
          "value": "CCBC94",
          "public": true,
          "usage": "Tier branding color",
          "deprecated": true
        },
        "200": {
          "value": "7F682E",
          "public": true,
          "usage": "Tier branding color",
          "deprecated": true
        }
      },
      "emerald": {
        "value": "139142",
        "public": true,
        "usage": "Tier branding color",
        "deprecated": true
      },
      "sapphire": {
        "value": "015DAA",
        "public": true,
        "usage": "Tier branding color",
        "deprecated": true
      },
      "ruby": {
        "value": "A41D4A",
        "public": true,
        "usage": "Tier branding color",
        "deprecated": true
      }
    }
  }
}
