{
  "color": {
    "tier": {
      "alaska": {
        "member": {
          "default": {
            "value": "{color.classic.grey.100.value}",
            "public": true,
            "usage": "",
            "wcag": "n/a",
            "deprecated": false
          },
          "inverse": {
            "value": "{color.classic.grey.100.value}",
            "public": true,
            "usage": "",
            "wcag": "n/a",
            "deprecated": false
          }
        },
        "mvp": {
          "default": {
            "value": "#726e6c",
            "public": true,
            "usage": "",
            "wcag": "n/a",
            "deprecated": false
          },
          "inverse": {
            "value": "c5c1bf",
            "public": true,
            "usage": "",
            "wcag": "n/a",
            "deprecated": false
          }
        },
        "mvpgold": {
          "default": {
            "value": "#7f682e",
            "public": true,
            "usage": "",
            "wcag": "n/a",
            "deprecated": false
          },
          "inverse": {
            "value": "#ccbc94",
            "public": true,
            "usage": "",
            "wcag": "n/a",
            "deprecated": false
          }
        },
        "mvp75k": {
          "default": {
            "value": "7f682e",
            "public": true,
            "usage": "",
            "wcag": "n/a",
            "deprecated": false
          },
          "inverse": {
            "value": "ccbc94",
            "public": true,
            "usage": "",
            "wcag": "n/a",
            "deprecated": false
          }
        },
        "mvp100k": {
          "default": {
            "value": "7f682e",
            "public": true,
            "usage": "",
            "wcag": "n/a",
            "deprecated": false
          },
          "inverse": {
            "value": "ccbc94",
            "public": true,
            "usage": "",
            "wcag": "n/a",
            "deprecated": false
          }
        }
      },
      "fare": {
        "saver": {
          "default": {
            "value": "{color.classic.cyan.500.value}",
            "public": true,
            "usage": "",
            "wcag": "n/a",
            "deprecated": false
          },
          "inverse": {
            "value": "{color.classic.cyan.200.value}",
            "public": true,
            "usage": "",
            "wcag": "n/a",
            "deprecated": false
          }
        },
        "economy": {
          "default": {
            "value": "{color.classic.blue.700.value}",
            "public": true,
            "usage": "",
            "wcag": "n/a",
            "deprecated": false
          },
          "inverse": {
            "value": "{color.classic.blue.300.value}",
            "public": true,
            "usage": "",
            "wcag": "n/a",
            "deprecated": false
          }
        },
        "business": {
          "default": {
            "value": "{color.classic.turquoise.800.value}",
            "public": true,
            "usage": "",
            "wcag": "n/a",
            "deprecated": false
          },
          "inverse": {
            "value": "{color.classic.turquoise.400.value}",
            "public": true,
            "usage": "",
            "wcag": "n/a",
            "deprecated": false
          }
        },
        "firstclass": {
          "default": {
            "value": "{color.classic.navy.1000.value}",
            "public": true,
            "usage": "",
            "wcag": "n/a",
            "deprecated": false
          },
          "inverse": {
            "value": "{color.classic.navy.400.value}",
            "public": true,
            "usage": "",
            "wcag": "n/a",
            "deprecated": false
          }
        }
      },
      "oneworld": {
        "emerald": {
          "value": "#139142",
          "public": true,
          "usage": "",
          "wcag": "n/a",
          "deprecated": false
        },
        "sapphire": {
          "value": "#015daa",
          "public": true,
          "usage": "",
          "wcag": "n/a",
          "deprecated": false
        },
        "ruby": {
          "value": "#a41d4a",
          "public": true,
          "usage": "",
          "wcag": "n/a",
          "deprecated": false
        }
      }
    }
  }
}
