{
  "basicTokens": {
    "color": {
      "border": {
        "bold": {
          "value": "#585E67"
        },
        "brand": {
          "value": "#00274A"
        },
        "divider": {
          "value": "#00000026"
        },
        "dividerInverse": {
          "value": "#FFFFFF66"
        },
        "inverse": {
          "value": "#FFFFFF"
        },
        "standard": {
          "value": "#959595"
        },
        "subtle": {
          "value": "#DDDDDD"
        }
      },
      "brand": {
        "primary": {
          "value": "#01426A"
        },
        "primaryBold": {
          "value": "#00274A"
        },
        "primaryMuted": {
          "value": "#EBF3F9"
        },
        "primarySubtle": {
          "value": "#2875B5"
        },
        "secondary": {
          "value": "#5DE3F7"
        },
        "secondaryBold": {
          "value": "#18C3DD"
        },
        "secondaryMuted": {
          "value": "#EBFAFD"
        },
        "secondarySubtle": {
          "value": "#B4EFF9"
        },
        "tertiary": {
          "value": "#A3CD6A"
        },
        "tertiaryBold": {
          "value": "#7DAF3B"
        },
        "tertiaryMuted": {
          "value": "#EAF3DD"
        },
        "tertiarySubtle": {
          "value": "#C9E1A7"
        }
      },
      "fare": {
        "basiceconomy": {
          "value": "#97EAF8"
        },
        "business": {
          "value": "#01426A"
        },
        "economy": {
          "value": "#0074CA"
        },
        "first": {
          "value": "#00274A"
        },
        "premiumeconomy": {
          "value": "#005154"
        }
      },
      "pageBackground": {
        "standard": {
          "value": "#FFFFFF"
        },
        "utility": {
          "value": "#FFFFFF"
        }
      },
      "status": {
        "error": {
          "value": "#E31F26"
        },
        "errorSubtle": {
          "value": "#FBC6C6"
        },
        "info": {
          "value": "#01426A"
        },
        "infoSubtle": {
          "value": "#EBF3F9"
        },
        "standard": {
          "value": "#AFB9C6"
        },
        "success": {
          "value": "#447A1F"
        },
        "successSubtle": {
          "value": "#D6EAC7"
        },
        "warning": {
          "value": "#FAC200"
        },
        "warningSubtle": {
          "value": "#FFF0B2"
        }
      },
      "surface": {
        "accent1": {
          "value": "#5DE3F7"
        },
        "accent1Muted": {
          "value": "#EBFAFD"
        },
        "accent1Subtle": {
          "value": "#B4EFF9"
        },
        "accent2": {
          "value": "#A3CD6A"
        },
        "accent2Muted": {
          "value": "#EAF3DD"
        },
        "inverse": {
          "value": "#00274A"
        },
        "inverseSubtle": {
          "value": "#2875B5"
        },
        "neutral": {
          "value": "#F2F2F2"
        },
        "neutralMedium": {
          "value": "#C5C5C5"
        },
        "neutralSubtle": {
          "value": "#F7F7F7"
        },
        "standard": {
          "value": "#FFFFFF"
        }
      },
      "textIcon": {
        "accent1": {
          "value": "#265688"
        },
        "disabled": {
          "value": "#D0D0D0"
        },
        "inverse": {
          "value": "#FFFFFF"
        },
        "inverseDisabled": {
          "value": "#7E8894"
        },
        "inverseMuted": {
          "value": "#CCD2DB"
        },
        "linkDefault": {
          "value": "#2875B5"
        },
        "linkHover": {
          "value": "#01426A"
        },
        "linkInverseDefault": {
          "value": "#FFFFFF"
        },
        "linkInverseHover": {
          "value": "#EBF3F9"
        },
        "muted": {
          "value": "#676767"
        },
        "standard": {
          "value": "#2A2A2A"
        }
      },
      "tierProgram": {
        "loungetier": {
          "lounge": {
            "value": "#01426A"
          },
          "loungeplus": {
            "value": "#53B390"
          }
        },
        "loyaltytier": {
          "gold": {
            "value": "#FBDC7A"
          },
          "goldMuted": {
            "value": "#FDEFC4"
          },
          "platinum": {
            "value": "#BCB8A4"
          },
          "platinumMuted": {
            "value": "#DAD8CD"
          },
          "silver": {
            "value": "#E4E9EC"
          },
          "silverMuted": {
            "value": "#F9FAFB"
          },
          "titanium": {
            "value": "#282828"
          },
          "titaniumMuted": {
            "value": "#545454"
          }
        },
        "oneworld": {
          "emerald": {
            "value": "#139142"
          },
          "ruby": {
            "value": "#A41D4A"
          },
          "sapphire": {
            "value": "#015DAA"
          }
        }
      }
    },
    "typography": {
      "accent2xl": {
        "fontFamily": "Good OT",
        "fontSize": 32,
        "fontWeight": "Cond News",
        "letterSpacing": 1.6,
        "lineHeight": "100%"
      },
      "accent2xs": {
        "fontFamily": "Good OT",
        "fontSize": 14,
        "fontWeight": "Cond News",
        "letterSpacing": 1.4,
        "lineHeight": "130%"
      },
      "accentlg": {
        "fontFamily": "Good OT",
        "fontSize": 24,
        "fontWeight": "Cond News",
        "letterSpacing": 1.2,
        "lineHeight": "130%"
      },
      "accentmd": {
        "fontFamily": "Good OT",
        "fontSize": 22,
        "fontWeight": "Cond Medium",
        "letterSpacing": 1.1,
        "lineHeight": "130%"
      },
      "accentsm": {
        "fontFamily": "Good OT",
        "fontSize": 18,
        "fontWeight": "Cond Medium",
        "letterSpacing": 0.9,
        "lineHeight": "130%"
      },
      "accentxl": {
        "fontFamily": "Good OT",
        "fontSize": 26,
        "fontWeight": "Cond News",
        "letterSpacing": 1.3,
        "lineHeight": "130%"
      },
      "accentxs": {
        "fontFamily": "Good OT",
        "fontSize": 16,
        "fontWeight": "Cond Medium",
        "letterSpacing": 1.6,
        "lineHeight": "130%"
      },
      "body2xs": {
        "fontFamily": "AS Circular",
        "fontSize": 10,
        "fontWeight": "Book",
        "letterSpacing": 0,
        "lineHeight": 14
      },
      "bodydefault": {
        "fontFamily": "AS Circular",
        "fontSize": 16,
        "fontWeight": "Book",
        "letterSpacing": 0,
        "lineHeight": 24
      },
      "bodylg": {
        "fontFamily": "AS Circular",
        "fontSize": 18,
        "fontWeight": "Book",
        "letterSpacing": 0,
        "lineHeight": 26
      },
      "bodysm": {
        "fontFamily": "AS Circular",
        "fontSize": 14,
        "fontWeight": "Book",
        "letterSpacing": 0,
        "lineHeight": 20
      },
      "bodyxs": {
        "fontFamily": "AS Circular",
        "fontSize": 12,
        "fontWeight": "Book",
        "letterSpacing": 0,
        "lineHeight": 16
      },
      "display2xl": {
        "fontFamily": "AS Circular",
        "fontSize": 56,
        "fontWeight": "Light",
        "letterSpacing": 0,
        "lineHeight": "130%"
      },
      "displaylg": {
        "fontFamily": "AS Circular",
        "fontSize": 44,
        "fontWeight": "Light",
        "letterSpacing": 0,
        "lineHeight": "130%"
      },
      "displaymd": {
        "fontFamily": "AS Circular",
        "fontSize": 40,
        "fontWeight": "Light",
        "letterSpacing": 0,
        "lineHeight": "130%"
      },
      "displaysm": {
        "fontFamily": "AS Circular",
        "fontSize": 32,
        "fontWeight": "Light",
        "letterSpacing": 0,
        "lineHeight": "130%"
      },
      "displayxl": {
        "fontFamily": "AS Circular",
        "fontSize": 48,
        "fontWeight": "Light",
        "letterSpacing": 0,
        "lineHeight": "130%"
      },
      "displayxs": {
        "fontFamily": "AS Circular",
        "fontSize": 28,
        "fontWeight": "Light",
        "letterSpacing": 0,
        "lineHeight": "130%"
      },
      "heading2xs": {
        "fontFamily": "AS Circular",
        "fontSize": 18,
        "fontWeight": "Book",
        "letterSpacing": 0,
        "lineHeight": "130%"
      },
      "headinglg": {
        "fontFamily": "AS Circular",
        "fontSize": 28,
        "fontWeight": "Light",
        "letterSpacing": 0,
        "lineHeight": "130%"
      },
      "headingmd": {
        "fontFamily": "AS Circular",
        "fontSize": 26,
        "fontWeight": "Light",
        "letterSpacing": 0,
        "lineHeight": "130%"
      },
      "headingsm": {
        "fontFamily": "AS Circular",
        "fontSize": 22,
        "fontWeight": "Light",
        "letterSpacing": 0,
        "lineHeight": "130%"
      },
      "headingxl": {
        "fontFamily": "AS Circular",
        "fontSize": 32,
        "fontWeight": "Light",
        "letterSpacing": 0,
        "lineHeight": "130%"
      },
      "headingxs": {
        "fontFamily": "AS Circular",
        "fontSize": 20,
        "fontWeight": "Book",
        "letterSpacing": 0,
        "lineHeight": "130%"
      }
    }
  },
  "themeMetadata": {
    "code": "asLight",
    "displayName": "Alaska Airlines",
    "iconUrl": "https://images.contentstack.io/v3/assets/blt2cefe12c88e9dd91/blt52aa7bbcad1a728f/favicon.ico",
    "name": "Alaska Airlines",
    "webviewCode": "auro.theme.alaska"
  },
  "uiTokens": {
    "button": {
      "disabled": {
        "background": {
          "value": "#0000000D"
        },
        "text": {
          "value": "#D0D0D0"
        }
      },
      "disabledInverse": {
        "background": {
          "value": "#FFFFFF0D"
        },
        "text": {
          "value": "#7E8894"
        }
      },
      "primary": {
        "background": {
          "value": "#01426A"
        },
        "backgroundPressed": {
          "value": "#00274A"
        },
        "text": {
          "value": "#FFFFFF"
        }
      },
      "primaryInverse": {
        "background": {
          "value": "#FFFFFF"
        },
        "backgroundPressed": {
          "value": "#FFFFFFCC"
        },
        "text": {
          "value": "#01426A"
        }
      },
      "quaternary": {
        "backgroundPressed": {
          "value": "#00274A"
        },
        "text": {
          "value": "#01426A"
        }
      },
      "quaternaryInverse": {
        "backgroundPressed": {
          "value": "#00274A"
        },
        "text": {
          "value": "#FFFFFF"
        }
      },
      "secondary": {
        "background": {
          "value": "#EBF3F9"
        },
        "backgroundPressed": {
          "value": "#AEDEFF"
        },
        "text": {
          "value": "#01426A"
        }
      },
      "secondaryInverse": {
        "background": {
          "value": "#EBF3F9"
        },
        "backgroundPressed": {
          "value": "#CFE0EF"
        },
        "text": {
          "value": "#01426A"
        }
      },
      "tertiary": {
        "background": {
          "value": "#00000012"
        },
        "backgroundPressed": {
          "value": "#0000001C"
        },
        "border": {
          "value": "#DDDDDD"
        },
        "text": {
          "value": "#01426A"
        }
      },
      "tertiaryInverse": {
        "background": {
          "value": "#FFFFFF12"
        },
        "backgroundPressed": {
          "value": "#FFFFFF1C"
        },
        "border": {
          "value": "#FFFFFF"
        },
        "text": {
          "value": "#FFFFFF"
        }
      }
    },
    "component": {
      "elevated": {
        "value": "#00000012"
      },
      "pressed": {
        "value": "#0000001C"
      },
      "selected": {
        "value": "#01426A"
      },
      "selectedMuted": {
        "value": "#EBF3F9"
      }
    },
    "componentInverse": {
      "elevated": {
        "value": "#FFFFFF12"
      },
      "error": {
        "value": "#F9A4A8"
      },
      "pressed": {
        "value": "#FFFFFF1C"
      },
      "selected": {
        "value": "#FFFFFF"
      },
      "selectedMuted": {
        "value": "#FFFFFFCC"
      }
    },
    "hyperlinkApp": {
      "text": {
        "value": "#2875B5"
      },
      "textHover": {
        "value": "#01426A"
      },
      "textInverse": {
        "value": "#FFFFFF"
      },
      "textInverseHover": {
        "value": "#EBF3F9"
      }
    },
    "searchWidget": {
      "fieldIcon": {
        "value": "#5DE3F7"
      },
      "routeDestination": {
        "value": "#A3CD6A"
      },
      "routeOrgin": {
        "value": "#5DE3F7"
      }
    }
  }
}
